{
  "talk": {
    "title1": "Swapy Exchange",
    "title2": "Swapy Financial ID",
    "title3": "Swapy DataMarket",
    "description1": "Swapy Exchange provides an innovative way to connect smart money to emerging economies, playing a big role in world’s development.",
    "description2": "Swapy Financial ID creates an universal financial identity for individuals and organizations, valid worldwide.",
    "description3": "Swapy DataMarket provide a huge financial data source where individuals have the rights and reap the value of their own data.",
    "question": "<b>Want to be part</b> of the <b>Credit Revolution?</b>",
    "answer": "Talk with us and find out how",
    "withUs": "Talk with us"
  }
}
